oblique/__init__.py
oblique/__main__.py
oblique/strategies.ini
oblique-25.5.0.dist-info/METADATA
oblique-25.5.0.dist-info/WHEEL
oblique-25.5.0.dist-info/entry_points.txt
oblique-25.5.0.dist-info/top_level.txt
oblique-25.5.0.dist-info/RECORD
