Metadata-Version: 2.4
Name: oblique
Version: 25.5.0
Summary: Show koans from Oblique Strategies
Author-email: Łukasz Langa <lukasz@langa.pl>
License: BSD-3-Clause
Project-URL: Homepage, https://github.com/ambv/oblique
Keywords: oblique strategies,brian eno,fortune
Requires-Python: >=3.9
Requires-Dist: click>=8.1.8
